[
  {
    "name": "Example AI Device",
    "description": "Short product summary from exhibitor or press kit.",
    "website": "https://example.com",
    "logo_url": "https://logo.clearbit.com/example.com",
    "categories": ["hardware", "voice"],
    "rating": 4.2,
    "weekly_users": 0,
    "trending_score": 78,
    "event": "CES",
    "event_year": 2026,
    "booth": "LVCC - North Hall 12345",
    "brand": "Example Labs",
    "release_year": 2026,
    "press_url": "https://example.com/press"
  }
]
